soak/__init__.py
soak/base.arid
soak/context.py
soak/soak.py
soak/terminal.py
soak/util.py
soak-40.dist-info/METADATA
soak-40.dist-info/WHEEL
soak-40.dist-info/entry_points.txt
soak-40.dist-info/top_level.txt
soak-40.dist-info/RECORD
