Metadata-Version: 2.1
Name: soak
Version: 40
Summary: Process aridity templates en masse, like Helm but much more DRY
Home-page: https://pypi.org/project/soak/
Author: foyono
Author-email: shrovis@foyono.com
Requires-Dist: aridity>=89
Requires-Dist: foyndation>=11
Requires-Dist: lagoon>=52
Requires-Dist: PyYAML>=5.2
